waralert/__init__.py
waralert/alert.py
waralert/send_email.py
waralert/trackers.py
waralert-0.0.6.dist-info/METADATA
waralert-0.0.6.dist-info/WHEEL
waralert-0.0.6.dist-info/top_level.txt
waralert-0.0.6.dist-info/RECORD
