Metadata-Version: 2.1
Name: waralert
Version: 0.0.6
Summary: This project is a very simplified version of a bug tracking and reporting system like Sentry
Home-page: https://github.com/themusharraf/waralert
Author: Musharraf Ibragimov
Author-email: meibrohimov@gmail.com
License: MIT
Classifier: License :: OSI Approved :: MIT License
Classifier: Programming Language :: Python
Classifier: Programming Language :: Python :: 3
Classifier: Programming Language :: Python :: 3.6
Classifier: Programming Language :: Python :: Implementation :: CPython
Classifier: Programming Language :: Python :: Implementation :: PyPy
Requires-Python: >=3.8.0
Requires-Dist: python-dotenv==1.0.1
